audiotree/__init__.py
audiotree/core.py
audiotree/loudness.py
audiotree/resample.py
audiotree/datasources/__init__.py
audiotree/datasources/core.py
audiotree/transforms/__init__.py
audiotree/transforms/base.py
audiotree/transforms/core.py
audiotree/transforms/helpers.py
audiotree-0.2.1.dist-info/licenses/LICENSE
audiotree-0.2.1.dist-info/METADATA
audiotree-0.2.1.dist-info/WHEEL
audiotree-0.2.1.dist-info/top_level.txt
audiotree-0.2.1.dist-info/RECORD
